b64image/__init__.py
b64image/base64_image.py
b64image/cli.py
b64image/imghdr.py
b64image/llm.py
b64image/py.typed
b64image-0.1.1.dist-info/METADATA
b64image-0.1.1.dist-info/WHEEL
b64image-0.1.1.dist-info/entry_points.txt
b64image-0.1.1.dist-info/top_level.txt
b64image-0.1.1.dist-info/RECORD
