Metadata-Version: 2.4
Name: b64image
Version: 0.1.1
Summary: Base64 image encoding/decoding with LLM API support
Requires-Python: >=3.12
